[
  {
    "title": "Neighborhood Garage Sale - ZIP 48439",
    "location": "1010 Neighborhood Circle, ZIP 48439",
    "description": "Hi neighbors! Having a garage sale this weekend. Kids toys, books, clothes, kitchen items, and some furniture. Everything priced to sell. Come browse and say hello!",
    "date": "2025-07-17",
    "price": "Various prices",
    "link": "https://nextdoor.com/sales/ZIP 48439",
    "source": "Nextdoor"
  },
  {
    "title": "Moving Sale - ZIP 48439",
    "location": "2020 Departure Street, ZIP 48439",
    "description": "We're moving across the country and need to downsize! Quality furniture, appliances, electronics, home decor, and more. Serious buyers welcome. Cash preferred.",
    "date": "2025-07-18",
    "price": "Everything must go!",
    "link": "https://nextdoor.com/moving-sale/ZIP 48439",
    "source": "Nextdoor"
  }
]